msg_explorer/__init__.py
msg_explorer/__main__.py
msg_explorer/_recompile.py
msg_explorer/app_icons.py
msg_explorer/app_icons.qrc
msg_explorer/attachments_browser.py
msg_explorer/constants.py
msg_explorer/font_handler.py
msg_explorer/guid_viewer.py
msg_explorer/hex_viewer.py
msg_explorer/logger.py
msg_explorer/logger_widget.py
msg_explorer/main.py
msg_explorer/main_window.py
msg_explorer/msg_details_page.py
msg_explorer/msg_tree_viewer.py
msg_explorer/multiple_binary_viewer.py
msg_explorer/multiple_viewer.py
msg_explorer/named_properties_viewer.py
msg_explorer/properties_viewer.py
msg_explorer/py.typed
msg_explorer/stream_viewer.py
msg_explorer/string_viewer.py
msg_explorer/utils.py
msg_explorer/icon/envelope_1024.png
msg_explorer/ui/__init__.py
msg_explorer/ui/attachments_browser.ui
msg_explorer/ui/guid_viewer.ui
msg_explorer/ui/hex_viewer.ui
msg_explorer/ui/loading_screen.ui
msg_explorer/ui/logger_widget.ui
msg_explorer/ui/main_window.ui
msg_explorer/ui/msg_details_page.ui
msg_explorer/ui/msg_tree_viewer.ui
msg_explorer/ui/multiple_binary_viewer.ui
msg_explorer/ui/multiple_viewer.ui
msg_explorer/ui/named_properties_viewer.ui
msg_explorer/ui/properties_viewer.ui
msg_explorer/ui/stream_viewer.ui
msg_explorer/ui/string_viewer.ui
msg_explorer/ui/unhandled_exception.ui
msg_explorer-1.7.0.dist-info/LICENSE.txt
msg_explorer-1.7.0.dist-info/METADATA
msg_explorer-1.7.0.dist-info/WHEEL
msg_explorer-1.7.0.dist-info/entry_points.txt
msg_explorer-1.7.0.dist-info/top_level.txt
msg_explorer-1.7.0.dist-info/RECORD
