Metadata-Version: 2.1
Name: msg-explorer
Version: 1.7.0
Summary: A GUI program to allow for exploring MSG files using extract-msg.
Home-page: https://github.com/TeamMsgExtractor/msg-explorer
Download-URL: https://github.com/TeamMsgExtractor/msg-explorer/archives/master
Author: Destiny Peterson
Author-email: arceusthe@gmail.com
License: GPL
Classifier: Development Status :: 5 - Production/Stable
Classifier: License :: OSI Approved :: GNU General Public License v3 (GPLv3)
Classifier: Operating System :: OS Independent
Classifier: Programming Language :: Python :: 3
Requires-Python: >=3.8
License-File: LICENSE.txt
Requires-Dist: extract-msg (<0.42,>=0.41.1)
Requires-Dist: PySide6 (<6.5,>=6.3.0)
